odoo/addons/account_cash_discount_base/README.rst
odoo/addons/account_cash_discount_base/__init__.py
odoo/addons/account_cash_discount_base/__manifest__.py
odoo/addons/account_cash_discount_base/i18n/account_cash_discount_base.pot
odoo/addons/account_cash_discount_base/i18n/es.po
odoo/addons/account_cash_discount_base/i18n/es_PA.po
odoo/addons/account_cash_discount_base/i18n/fr.po
odoo/addons/account_cash_discount_base/migrations/10.0.1.0.0/pre-migration.py
odoo/addons/account_cash_discount_base/models/__init__.py
odoo/addons/account_cash_discount_base/models/account_move.py
odoo/addons/account_cash_discount_base/models/account_payment_term.py
odoo/addons/account_cash_discount_base/models/res_company.py
odoo/addons/account_cash_discount_base/readme/CONTRIBUTORS.rst
odoo/addons/account_cash_discount_base/readme/DESCRIPTION.rst
odoo/addons/account_cash_discount_base/readme/USAGE.rst
odoo/addons/account_cash_discount_base/reports/report_invoice.xml
odoo/addons/account_cash_discount_base/static/description/icon.png
odoo/addons/account_cash_discount_base/static/description/index.html
odoo/addons/account_cash_discount_base/tests/__init__.py
odoo/addons/account_cash_discount_base/tests/common.py
odoo/addons/account_cash_discount_base/tests/test_account_cash_discount_base.py
odoo/addons/account_cash_discount_base/views/account_move.xml
odoo/addons/account_cash_discount_base/views/account_payment_term.xml
odoo/addons/account_cash_discount_base/views/res_company.xml
odoo14_addon_account_cash_discount_base-14.0.1.0.1.dev7.dist-info/METADATA
odoo14_addon_account_cash_discount_base-14.0.1.0.1.dev7.dist-info/WHEEL
odoo14_addon_account_cash_discount_base-14.0.1.0.1.dev7.dist-info/top_level.txt
odoo14_addon_account_cash_discount_base-14.0.1.0.1.dev7.dist-info/RECORD
